{"is_source_file": true, "format": "TypeScript", "description": "This file defines an Angular service called RecipeService that provides methods to retrieve recipe data, either from in-memory mock data or potentially from an API in the future. It includes methods to get all recipes and a specific recipe by ID.", "external_files": ["../models/recipe"], "external_methods": ["inject", "of"], "published": ["RecipeService"], "classes": [{"name": "RecipeService", "description": "Angular service that offers methods to access recipe data, both mock and real."}], "methods": [{"name": "getRecipes(): Observable<Recipe[]> { getRecipes", "description": "Returns an Observable of the list of recipes, currently from in-memory data, with a placeholder for API integration.", "scope": "RecipeService", "scopeKind": "class"}, {"name": "getRecipe(id: number): Observable<Recipe | undefined> { getRecipe", "description": "Returns an Observable of a single recipe by its ID, using in-memory data, with a placeholder for API integration.", "scope": "RecipeService", "scopeKind": "class"}], "calls": ["inject(EnvironmentInjector)", "of(this.recipes)", "this.recipes.find(r => r.id === id)"], "search-terms": ["RecipeService", "@Injectable", "getRecipes", "getRecipe", "recipe data", "Angular service", "mock data"], "state": 2, "file_id": 22, "knowledge_revision": 71, "git_revision": "c161483aa8a3bd56414353c99a7778896c83e083", "revision_history": [{"46": ""}, {"71": "c161483aa8a3bd56414353c99a7778896c83e083"}], "ctags": [{"_type": "tag", "name": "RecipeService", "path": "/home/kavia/workspace/code-generation/simple-recipe-viewer-44390-44399/frontend/src/app/services/recipe.service.ts", "pattern": "/^export class RecipeService {$/", "language": "TypeScript", "kind": "class"}, {"_type": "tag", "name": "apiBase", "path": "/home/kavia/workspace/code-generation/simple-recipe-viewer-44390-44399/frontend/src/app/services/recipe.service.ts", "pattern": "/^  private readonly apiBase = '';$/", "language": "TypeScript", "kind": "property", "scope": "RecipeService", "scopeKind": "class"}, {"_type": "tag", "name": "getRecipe", "path": "/home/kavia/workspace/code-generation/simple-recipe-viewer-44390-44399/frontend/src/app/services/recipe.service.ts", "pattern": "/^  getRecipe(id: number): Observable<Recipe | undefined> {$/", "language": "TypeScript", "kind": "method", "scope": "RecipeService", "scopeKind": "class"}, {"_type": "tag", "name": "getRecipes", "path": "/home/kavia/workspace/code-generation/simple-recipe-viewer-44390-44399/frontend/src/app/services/recipe.service.ts", "pattern": "/^  getRecipes(): Observable<Recipe[]> {$/", "language": "TypeScript", "kind": "method", "scope": "RecipeService", "scopeKind": "class"}, {"_type": "tag", "name": "recipes", "path": "/home/kavia/workspace/code-generation/simple-recipe-viewer-44390-44399/frontend/src/app/services/recipe.service.ts", "pattern": "/^  private recipes: Recipe[] = [$/", "language": "TypeScript", "kind": "property", "scope": "RecipeService", "scopeKind": "class"}], "hash": "5f9444059790716581f1393338ba29e6", "format-version": 4, "code-base-name": "frontend", "filename": "frontend/src/app/services/recipe.service.ts", "fields": [{"name": "private readonly apiBase = '';", "scope": "RecipeService", "scopeKind": "class", "description": "unavailable"}, {"name": "private recipes: Recipe[] = [", "scope": "RecipeService", "scopeKind": "class", "description": "unavailable"}]}