{"is_source_file": true, "format": "TypeScript", "description": "Defines the Recipe interface for a recipe object in the frontend application.", "external_files": [], "external_methods": [], "published": ["Recipe"], "classes": [], "methods": [], "calls": [], "search-terms": ["Recipe", "interface", "typescript", "recipe model", "ingredients", "instructions"], "state": 2, "file_id": 21, "knowledge_revision": 43, "git_revision": "", "ctags": [{"_type": "tag", "name": "Recipe", "path": "/home/kavia/workspace/code-generation/simple-recipe-viewer-44390-44399/frontend/src/app/models/recipe.ts", "pattern": "/^export interface Recipe {$/", "language": "TypeScript", "kind": "interface"}, {"_type": "tag", "name": "cookTime", "path": "/home/kavia/workspace/code-generation/simple-recipe-viewer-44390-44399/frontend/src/app/models/recipe.ts", "pattern": "/^  cookTime?: string;$/", "language": "TypeScript", "kind": "property", "scope": "Recipe", "scopeKind": "interface"}, {"_type": "tag", "name": "description", "path": "/home/kavia/workspace/code-generation/simple-recipe-viewer-44390-44399/frontend/src/app/models/recipe.ts", "pattern": "/^  description: string;$/", "language": "TypeScript", "kind": "property", "scope": "Recipe", "scopeKind": "interface"}, {"_type": "tag", "name": "id", "path": "/home/kavia/workspace/code-generation/simple-recipe-viewer-44390-44399/frontend/src/app/models/recipe.ts", "pattern": "/^  id: number;$/", "language": "TypeScript", "kind": "property", "scope": "Recipe", "scopeKind": "interface"}, {"_type": "tag", "name": "image", "path": "/home/kavia/workspace/code-generation/simple-recipe-viewer-44390-44399/frontend/src/app/models/recipe.ts", "pattern": "/^  image: string;$/", "language": "TypeScript", "kind": "property", "scope": "Recipe", "scopeKind": "interface"}, {"_type": "tag", "name": "ingredients", "path": "/home/kavia/workspace/code-generation/simple-recipe-viewer-44390-44399/frontend/src/app/models/recipe.ts", "pattern": "/^  ingredients: string[];$/", "language": "TypeScript", "kind": "property", "scope": "Recipe", "scopeKind": "interface"}, {"_type": "tag", "name": "instructions", "path": "/home/kavia/workspace/code-generation/simple-recipe-viewer-44390-44399/frontend/src/app/models/recipe.ts", "pattern": "/^  instructions: string;$/", "language": "TypeScript", "kind": "property", "scope": "Recipe", "scopeKind": "interface"}, {"_type": "tag", "name": "prepTime", "path": "/home/kavia/workspace/code-generation/simple-recipe-viewer-44390-44399/frontend/src/app/models/recipe.ts", "pattern": "/^  prepTime?: string;$/", "language": "TypeScript", "kind": "property", "scope": "Recipe", "scopeKind": "interface"}, {"_type": "tag", "name": "title", "path": "/home/kavia/workspace/code-generation/simple-recipe-viewer-44390-44399/frontend/src/app/models/recipe.ts", "pattern": "/^  title: string;$/", "language": "TypeScript", "kind": "property", "scope": "Recipe", "scopeKind": "interface"}], "hash": "5183baf74436afef6545aed65b8e58eb", "format-version": 4, "code-base-name": "frontend", "filename": "frontend/src/app/models/recipe.ts", "fields": [{"name": "export interface Recipe {", "scope": "", "scopeKind": "", "description": "unavailable"}, {"name": "cookTime?: string;", "scope": "Recipe", "scopeKind": "interface", "description": "unavailable"}, {"name": "description: string;", "scope": "Recipe", "scopeKind": "interface", "description": "unavailable"}, {"name": "id: number;", "scope": "Recipe", "scopeKind": "interface", "description": "unavailable"}, {"name": "image: string;", "scope": "Recipe", "scopeKind": "interface", "description": "unavailable"}, {"name": "ingredients: string[];", "scope": "Recipe", "scopeKind": "interface", "description": "unavailable"}, {"name": "instructions: string;", "scope": "Recipe", "scopeKind": "interface", "description": "unavailable"}, {"name": "prepTime?: string;", "scope": "Recipe", "scopeKind": "interface", "description": "unavailable"}, {"name": "title: string;", "scope": "Recipe", "scopeKind": "interface", "description": "unavailable"}], "revision_history": [{"43": ""}]}